simpel_captcha/__init__.py
simpel_captcha/font/FangZhengFangSongJianTi-1.ttf
simpel_captcha/src.py
simpel_captcha-0.1.4.dist-info/LICENSE
simpel_captcha-0.1.4.dist-info/WHEEL
simpel_captcha-0.1.4.dist-info/METADATA
simpel_captcha-0.1.4.dist-info/RECORD
