Metadata-Version: 2.1
Name: simpel-captcha
Version: 0.1.4
Summary: FastAPI or starlette 生成验证码(图片/文字) 提供 io/ base64/ 本地文件存储方式
Home-page: https://github.com/zy7y/simpel_captcha
License: MIT
Keywords: FastAPI,captcha,starlette,simpel,easy,base64
Author: 柒意
Author-email: 396667207@qq.com
Requires-Python: >=3.6,<4.0
Classifier: License :: OSI Approved :: MIT License
Classifier: Programming Language :: Python :: 3
Classifier: Programming Language :: Python :: 3.6
Classifier: Programming Language :: Python :: 3.7
Classifier: Programming Language :: Python :: 3.8
Classifier: Programming Language :: Python :: 3.9
Classifier: Programming Language :: Python :: 3.10
Classifier: Programming Language :: Python :: 3.11
Requires-Dist: Pillow (>=8.4.0,<9.0.0)
Project-URL: Repository, https://github.com/zy7y/simpel_captcha
